pytezos_crypto/encoding.py
pytezos_crypto/key.py
pytezos_crypto-3.13.4.1.dist-info/METADATA
pytezos_crypto-3.13.4.1.dist-info/WHEEL
pytezos_crypto-3.13.4.1.dist-info/licenses/AUTHORS.rst
pytezos_crypto-3.13.4.1.dist-info/licenses/LICENSE.txt
pytezos_crypto-3.13.4.1.dist-info/RECORD
