Metadata-Version: 2.4
Name: pytezos-crypto
Version: 3.13.4.1
Summary: Cryptographic utilities from PyTezos
Project-URL: Issues, https://github.com/aleph-im/pytezos-crypto/issues
Project-URL: Source, https://github.com/aleph-im/pytezos-crypto
Author: Arthur Breitman, Roman Serikov
Author-email: Michael Zaikin <mz@baking-bad.org>, Lev Gorodetskii <pytezos@drsr.io>, Igor Sereda <sereda.igor.s@gmail.com>, Olivier Desenfans <desenfans.olivier@gmail.com>, Hugo Herter <git@hugoherter.com>
Maintainer-email: Hugo Herter <git@hugoherter.com>
License: MIT License
License-File: AUTHORS.rst
License-File: LICENSE.txt
Keywords: blockchain,crypto,cryptocurrencies,sdk,tezos
Classifier: Development Status :: 5 - Production/Stable
Classifier: Environment :: Console
Classifier: Intended Audience :: Developers
Classifier: License :: OSI Approved :: MIT License
Classifier: Operating System :: OS Independent
Classifier: Programming Language :: Python :: 3 :: Only
Classifier: Programming Language :: Python :: 3.9
Classifier: Programming Language :: Python :: 3.10
Classifier: Programming Language :: Python :: 3.11
Classifier: Programming Language :: Python :: 3.12
Classifier: Topic :: Software Development :: Libraries :: Python Modules
Classifier: Typing :: Typed
Requires-Python: >=3.9
Requires-Dist: base58
Requires-Dist: coincurve>=20
Requires-Dist: fastecdsa
Requires-Dist: libnacl
Requires-Dist: mnemonic
Provides-Extra: testing
Requires-Dist: pytest; extra == 'testing'
Requires-Dist: pytest-cov; extra == 'testing'
